setup.py
djangorestframework_extensions/__init__.py
djangorestframework_extensions/authentication.py
djangorestframework_extensions/mixins.py
djangorestframework_extensions/models.py
djangorestframework_extensions/permissions.py
djangorestframework_extensions/renderers.py
djangorestframework_extensions/resources.py
djangorestframework_extensions/serializer.py
djangorestframework_extensions/utils.py
djangorestframework_extensions.egg-info/PKG-INFO
djangorestframework_extensions.egg-info/SOURCES.txt
djangorestframework_extensions.egg-info/dependency_links.txt
djangorestframework_extensions.egg-info/top_level.txt