Metadata-Version: 1.0
Name: djangorestframework-extensions
Version: 0.0.3
Summary: Extensions to django-rest-framework, which is a lightweight REST framework for Django.
Home-page: http://github.com.org/bolster/djangorestframework_extensions
Author: Bolster Labs, Inc.
Author-email: info@bolsterlabs.com
License: BSD
Platform: UNKNOWN
Classifier: Development Status :: 3 - Alpha
Classifier: Environment :: Web Environment
Classifier: Framework :: Django
Classifier: Intended Audience :: Developers
Classifier: License :: OSI Approved :: BSD License
Classifier: Operating System :: OS Independent
Classifier: Programming Language :: Python
Classifier: Topic :: Internet :: WWW/HTTP
